jobcant/__init__.py
jobcant/cli.py
jobcant/config.py
jobcant/duration.py
jobcant/jobcan.py
jobcant/plotting.py
Jobcant-1.5.0.dist-info/LICENSE
Jobcant-1.5.0.dist-info/METADATA
Jobcant-1.5.0.dist-info/WHEEL
Jobcant-1.5.0.dist-info/entry_points.txt
Jobcant-1.5.0.dist-info/top_level.txt
Jobcant-1.5.0.dist-info/RECORD
